setup.py
Treepace.egg-info/PKG-INFO
Treepace.egg-info/SOURCES.txt
Treepace.egg-info/dependency_links.txt
Treepace.egg-info/requires.txt
Treepace.egg-info/top_level.txt
treepace/__init__.py
treepace/base.py
treepace/build.py
treepace/compiler.py
treepace/formats.py
treepace/instructions.py
treepace/nodes.py
treepace/relations.py
treepace/replace.py
treepace/search.py
treepace/trees.py
treepace/utils.py
treepace/examples/__init__.py
treepace/examples/document.py
treepace/examples/gui.py